hydrosim/__init__.py
hydrosim/cli.py
hydrosim/climate.py
hydrosim/climate_engine.py
hydrosim/climate_sources.py
hydrosim/config.py
hydrosim/controls.py
hydrosim/exceptions.py
hydrosim/help.py
hydrosim/hydraulics.py
hydrosim/links.py
hydrosim/nodes.py
hydrosim/results.py
hydrosim/results_viz.py
hydrosim/simulation.py
hydrosim/solver.py
hydrosim/strategies.py
hydrosim/visualization.py
hydrosim/wgen.py
hydrosim/wgen_params.py
hydrosim/climate_builder/__init__.py
hydrosim/climate_builder/data_models.py
hydrosim/climate_builder/data_quality.py
hydrosim/climate_builder/dly_parser.py
hydrosim/climate_builder/ghcn_fetcher.py
hydrosim/climate_builder/parameter_csv.py
hydrosim/climate_builder/parameter_generator.py
hydrosim/climate_builder/precipitation_params.py
hydrosim/climate_builder/project_structure.py
hydrosim/climate_builder/solar_params.py
hydrosim/climate_builder/temperature_params.py
hydrosim-0.4.4.dist-info/licenses/LICENSE
scripts/dev_tools.py
hydrosim-0.4.4.dist-info/METADATA
hydrosim-0.4.4.dist-info/WHEEL
hydrosim-0.4.4.dist-info/entry_points.txt
hydrosim-0.4.4.dist-info/top_level.txt
hydrosim-0.4.4.dist-info/RECORD
