Metadata-Version: 2.4
Name: hydrosim
Version: 0.4.4
Summary: A Python framework for water resources planning with daily timestep simulation
Author: J. Lillywh
Maintainer: J. Lillywh
Project-URL: Homepage, https://github.com/jlillywh/hydrosim
Project-URL: Repository, https://github.com/jlillywh/hydrosim
Project-URL: Bug Reports, https://github.com/jlillywh/hydrosim/issues
Project-URL: Documentation, https://github.com/jlillywh/hydrosim#readme
Project-URL: Changelog, https://github.com/jlillywh/hydrosim/blob/main/CHANGELOG.md
Keywords: hydrology,water-resources,simulation,optimization,network-flow,reservoir
Classifier: Development Status :: 3 - Alpha
Classifier: Intended Audience :: Science/Research
Classifier: Topic :: Scientific/Engineering :: Hydrology
Classifier: Programming Language :: Python :: 3
Classifier: Programming Language :: Python :: 3.8
Classifier: Programming Language :: Python :: 3.9
Classifier: Programming Language :: Python :: 3.10
Classifier: Programming Language :: Python :: 3.11
Classifier: Programming Language :: Python :: 3.12
Requires-Python: >=3.8
License-File: LICENSE
Requires-Dist: numpy>=1.24.0
Requires-Dist: pandas>=2.0.0
Requires-Dist: scipy>=1.10.0
Requires-Dist: networkx>=3.0
Requires-Dist: pyyaml>=6.0
Requires-Dist: plotly>=5.0.0
Requires-Dist: requests>=2.25.0
Provides-Extra: dev
Requires-Dist: pytest>=7.4.0; extra == "dev"
Requires-Dist: hypothesis>=6.82.0; extra == "dev"
Requires-Dist: pytest-cov>=4.1.0; extra == "dev"
Dynamic: license-file
